ytdownloader/__init__.py
ytdownloader/command_line.py
ytdownloader-0.1.14.dist-info/METADATA
ytdownloader-0.1.14.dist-info/RECORD
ytdownloader-0.1.14.dist-info/WHEEL
ytdownloader-0.1.14.dist-info/entry_points.txt
ytdownloader-0.1.14.dist-info/top_level.txt
