Metadata-Version: 2.1
Name: ytdownloader
Version: 0.1.14
Summary: An automation service to download videos from Youtube
Home-page: https://github.com/mukultaneja/YoutubeDownloader
Author: mukultaneja
Author-email: mukultaneja91@gmail.com
License: MIT License
Project-URL: Source, https://github.com/mukultaneja/YoutubeDownloader
Project-URL: Bug Reports, https://github.com/mukultaneja/YoutubeDownloader/issues
Keywords: youtube download downloader videos playlist
Platform: UNKNOWN
Classifier: Environment :: Console
Classifier: Intended Audience :: System Administrators
Classifier: Intended Audience :: Developers
Classifier: Operating System :: POSIX :: Linux
Classifier: Operating System :: MacOS :: MacOS X
Classifier: Operating System :: Microsoft :: Windows
Classifier: Programming Language :: Python
Classifier: Programming Language :: Python :: 2.7
Classifier: Programming Language :: Python :: 3
Classifier: Programming Language :: Python :: 3.5
Classifier: Programming Language :: Python :: 3.6
Requires-Python: >=2.7
Requires-Dist: pyyaml
Requires-Dist: youtube-dl
